jupyter_server_kernels_proxy/__init__.py
jupyter_server_kernels_proxy/app.py
jupyter_server_kernels_proxy/kernels/handlers.py
jupyter_server_kernels_proxy/kernels/websocket.py
jupyter_server_kernels_proxy/sessions/handlers.py
jupyter_server_kernels_proxy-0.1.0.data/data/etc/jupyter/jupyter_server_config.d/jupyter_server_kernels_proxy.json
jupyter_server_kernels_proxy-0.1.0.dist-info/METADATA
jupyter_server_kernels_proxy-0.1.0.dist-info/WHEEL
jupyter_server_kernels_proxy-0.1.0.dist-info/licenses/LICENSE
jupyter_server_kernels_proxy-0.1.0.dist-info/RECORD
