Metadata-Version: 2.1
Name: jupyter_server_kernels_proxy
Version: 0.1.0
Summary: A Jupyter Server Extension Proxying Kernels.
Project-URL: Homepage, https://github.com/davidbrochart/jupyter_server_kernels_proxy
Author-email: David Brochart <david.brochart@gmail.com>
License: MIT License
License-File: LICENSE
Keywords: ipython,jupyter
Classifier: Intended Audience :: Developers
Classifier: Intended Audience :: Science/Research
Classifier: Intended Audience :: System Administrators
Classifier: License :: OSI Approved :: MIT License
Classifier: Programming Language :: Python
Classifier: Programming Language :: Python :: 3.7
Classifier: Programming Language :: Python :: 3.8
Classifier: Programming Language :: Python :: 3.9
Classifier: Programming Language :: Python :: 3.10
Classifier: Programming Language :: Python :: 3.11
Requires-Python: >=3.7
Requires-Dist: httpx>=0.23.1
Requires-Dist: jupyter-server>=2.0.0rc7
Requires-Dist: websockets>=10.4
